resotolib/__init__.py
resotolib/args.py
resotolib/baseplugin.py
resotolib/baseresources.py
resotolib/config.py
resotolib/durations.py
resotolib/event.py
resotolib/json.py
resotolib/json_bender.py
resotolib/jwt.py
resotolib/lock.py
resotolib/logger.py
resotolib/parse_util.py
resotolib/proc.py
resotolib/py.typed
resotolib/threading.py
resotolib/tree.py
resotolib/types.py
resotolib/units.py
resotolib/utils.py
resotolib/x509.py
resotolib/asynchronous/__init__.py
resotolib/asynchronous/utils.py
resotolib/asynchronous/web/__init__.py
resotolib/asynchronous/web/runner.py
resotolib/asynchronous/web/ws_handler.py
resotolib/core/__init__.py
resotolib/core/actions.py
resotolib/core/ca.py
resotolib/core/config.py
resotolib/core/custom_command.py
resotolib/core/events.py
resotolib/core/model_check.py
resotolib/core/model_export.py
resotolib/core/progress.py
resotolib/core/search.py
resotolib/core/tasks.py
resotolib/graph/__init__.py
resotolib/graph/graph_extensions.py
resotolib/log/__init__.py
resotolib/web/__init__.py
resotolib/web/metrics.py
resotolib/web/static/android-chrome-192x192.png
resotolib/web/static/android-chrome-512x512.png
resotolib/web/static/apple-touch-icon.png
resotolib/web/static/browserconfig.xml
resotolib/web/static/favicon-16x16.png
resotolib/web/static/favicon-32x32.png
resotolib/web/static/index.html
resotolib/web/static/mstile-150x150.png
resotolib/web/static/picnic.min.css
resotolib/web/static/site.webmanifest
resotolib-3.9.0.dist-info/METADATA
resotolib-3.9.0.dist-info/WHEEL
resotolib-3.9.0.dist-info/top_level.txt
resotolib-3.9.0.dist-info/RECORD
